webduino_core/.gitignore
webduino_core/client/__init__.py
webduino_core/client/_client_error.py
webduino_core/client/_client_example.py
webduino_core/client/_client_service.py
webduino_core/client/util/__init__.py
webduino_core/client/util/_convertor.py
webduino_core/client/util/_mqtt.py
webduino_core/common/rpc/__init__.py
webduino_core/common/rpc/_rpc_interface.py
webduino_core/common/rpc/_rpc_schema.py
webduino_core/common/rpc/base/__init__.py
webduino_core/common/rpc/base/_base_schema.py
webduino_core/common/rpc/base/_get_version_rpc.py
webduino_core/common/rpc/base/_set_wifi_rpc.py
webduino_core/common/rpc/thlisms/__init__.py
webduino_core/common/rpc/thlisms/_set_config_rpc.py
webduino_core/common/rpc/thlisms/_thlisms_schema.py
webduino_core/common/rpc/wfsrl/__init__.py
webduino_core/common/rpc/wfsrl/_set_config_rpc.py
webduino_core/common/rpc/wfsrl/_wfsrl_schema.py
webduino_core/common/util/__init__.py
webduino_core/common/util/_convertor.py
webduino_core/common/util/_dataclass.py
webduino_core/common/util/_filter.py
webduino_core/common/util/_validator.py
webduino_core/device/.gitignore
webduino_core/device/.tool-versions
webduino_core/device/__init__.py
webduino_core/device/_device_error.py
webduino_core/device/_device_example.py
webduino_core/device/_device_handler.py
webduino_core/device/_device_schema.py
webduino_core/device/_device_service.py
webduino_core/device/requirements.txt
webduino_core/device/util/__init__.py
webduino_core/device/util/_log.py
webduino_core/device/util/_memory.py
webduino_core/device/util/_mqtt.py
webduino_core/env.example.py
webduino_core-0.9.4.dist-info/WHEEL
webduino_core-0.9.4.dist-info/METADATA
webduino_core-0.9.4.dist-info/RECORD
