Metadata-Version: 2.1
Name: webduino_core
Version: 0.9.4
Summary: Webduino Core
Requires-Python: >=3.10
Requires-Dist: asyncio-mqtt==0.12.1
Requires-Dist: pydantic>=1.9.1
